crashvb_logging_utilities/__init__.py
crashvb_logging_utilities/click.py
crashvb_logging_utilities/logging.py
crashvb_logging_utilities/utils.py
tests/__init__.py
crashvb_logging_utilities-0.1.1.dist-info/LICENSE.md
crashvb_logging_utilities-0.1.1.dist-info/METADATA
crashvb_logging_utilities-0.1.1.dist-info/WHEEL
crashvb_logging_utilities-0.1.1.dist-info/top_level.txt
crashvb_logging_utilities-0.1.1.dist-info/RECORD
