Metadata-Version: 2.1
Name: crashvb-logging-utilities
Version: 0.1.1
Summary: Consolidation of logging utilities.
Home-page: https://pypi.org/project/crashvb-logging-utilities/
Author: Richard Davis
Author-email: crashvb@gmail.com
License: Apache License 2.0
Project-URL: Bug Reports, https://github.com/server27nw/crashvb-logging-utilities/issues
Project-URL: Source, https://github.com/server27nw/crashvb-logging-utilities
Keywords: crashvb logging utilities
Platform: UNKNOWN
Classifier: Development Status :: 4 - Beta
Classifier: Intended Audience :: End Users/Desktop
Classifier: License :: OSI Approved :: Apache Software License
Classifier: Programming Language :: Python :: 3
Classifier: Programming Language :: Python :: 3.8
Classifier: Programming Language :: Python :: 3.9
Classifier: Programming Language :: Python :: 3.10
Classifier: Operating System :: POSIX :: Linux
License-File: LICENSE.md
Requires-Dist: click
Provides-Extra: dev
Requires-Dist: black; extra == "dev"
Requires-Dist: coveralls; extra == "dev"
Requires-Dist: pylint; extra == "dev"
Requires-Dist: pytest; extra == "dev"
Requires-Dist: pytest-cov; extra == "dev"
Requires-Dist: twine; extra == "dev"
Requires-Dist: wheel; extra == "dev"
